.gitignore
.travis.yml
LICENSE
MANIFEST.in
README.rst
requirements.in
requirements.txt
requirements_test.in
requirements_test.txt
setup.cfg
setup.py
bin/pylleo-cal
doc/Makefile
doc/make.bat
doc/source/api.rst
doc/source/calibration.rst
doc/source/conf.py
doc/source/docs.rst
doc/source/guide.rst
doc/source/index.rst
doc/source/lleocal.rst
doc/source/lleoio.rst
doc/source/images/cal/s1.png
doc/source/images/cal/s2.png
doc/source/images/cal/t1.png
doc/source/images/cal/t2.png
doc/source/images/cal/t3.png
doc/source/images/cal/t4.png
doc/source/images/calapp/button_axes.png
doc/source/images/calapp/button_indices.png
doc/source/images/calapp/button_poly.png
doc/source/images/calapp/input_indices.png
doc/source/images/calapp/input_parent.png
doc/source/images/calapp/plot_hilo.png
doc/source/images/calapp/plot_hilo.xcf
doc/source/images/calapp/screen_start.png
doc/source/images/calapp/select_bound.png
doc/source/images/calapp/select_box-bound.png
doc/source/images/calapp/select_datadirs.png
doc/source/images/calapp/select_parameter.png
doc/source/images/calapp/terminal_poly-error.png
doc/source/images/calapp/terminal_poly-success.png
doc/source/images/calapp/terminal_start.png
doc/source/images/calapp/terminal_update-success.png
doc/source/images/calapp/tool_boxselect.png
doc/source/images/calapp/tool_boxzoom.png
doc/source/images/calapp/tool_hover.png
doc/source/images/calapp/tool_pan.png
doc/source/images/calapp/tool_wheel.png
doc/source/images/calapp/zoom_box-bound.png
doc/source/images/calapp/zoom_box-region.png
src/pylleo/__init__.py
src/pylleo/_version.py
src/pylleo/lleocal.py
src/pylleo/lleoio.py
src/pylleo/utils.py
src/pylleo/utils_bokeh.py
src/pylleo.egg-info/PKG-INFO
src/pylleo.egg-info/SOURCES.txt
src/pylleo.egg-info/dependency_links.txt
src/pylleo.egg-info/not-zip-safe
src/pylleo.egg-info/requires.txt
src/pylleo.egg-info/top_level.txt
src/pylleo/calapp/main.py
src/pylleo/calapp/templates/index.html
tests/__init__.py
tests/test_utils.py