Metadata-Version: 1.1
Name: pylleo
Version: 0.4.2
Summary: Utilities for working with Little Leonardo datalogger data in Python
Home-page: https://github.com/ryanjdillon/pylleo
Author: Ryan J. Dillon
Author-email: ryanjamesdillon@gmail.com
License: GPL-3.0+
Keywords: datalogger,accelerometer,biotelemetry
Platform: UNKNOWN
Classifier: Development Status :: 3 - Alpha
Classifier: Intended Audience :: Science/Research
Classifier: Programming Language :: Python :: 3.5
